xyzToPdb/__init__.py
xyzToPdb/__main__.py
xyzToPdb/model.py
xyztopdb-0.1.7.dist-info/LICENSE
xyztopdb-0.1.7.dist-info/METADATA
xyztopdb-0.1.7.dist-info/WHEEL
xyztopdb-0.1.7.dist-info/entry_points.txt
xyztopdb-0.1.7.dist-info/top_level.txt
xyztopdb-0.1.7.dist-info/RECORD
