Metadata-Version: 2.2
Name: xyzToPdb
Version: 0.1.7
Summary: xyztopdb file.xyz
License: MIT
Project-URL: Homepage, https://github.com/log-md/xyzToPdb
Classifier: Programming Language :: Python :: 3
Classifier: Operating System :: OS Independent
Requires-Python: >=3.8
License-File: LICENSE
Requires-Dist: torch>=2.0.0
Requires-Dist: numpy
Requires-Dist: scipy
Requires-Dist: ase
